LICENSE
MANIFEST.in
README.md
setup.py
biano/__init__.py
biano/__main__.py
biano/bzkb.py
biano/cache.py
biano/confkeys.py
biano/ioc.py
biano/kb.py
biano/keys.py
biano/keysbk.py
biano/play.py
biano/pynkb.py
biano/replay.py
biano/sound1.py
biano/tools.py
biano.egg-info/PKG-INFO
biano.egg-info/SOURCES.txt
biano.egg-info/dependency_links.txt
biano.egg-info/requires.txt
biano.egg-info/top_level.txt
biano/res/conf.js
biano/res/default_env.js
biano/res/hard.js
biano/res/datas/conf.js
biano/res/datas/left.js
biano/res/datas/right.js
biano/res/ioc/base.js
biano/res/ioc/cache.js
biano/res/ioc/keys.js
biano/res/ioc/main.js
biano/res/ioc/play.js
biano/res/ioc/sound.js
biano/test/ptest.py
biano/test/rtest.py
biano/test/sintest.py
biano/test/sound.py
biano/test/test.py
biano/test/test1.py