Metadata-Version: 2.1
Name: biano
Version: 0.3.2
Summary: keyboard piano, just start
Home-page: https://github.com/buildCodeZ/biano
Author: Zzz
Author-email: 1309458652@qq.com
License: Apache License 2.0
Keywords: biano
Platform: any
License-File: LICENSE
